{
    "HeadBone_stretch": 50,
    "HeadBone_shrink": 51,
    "HeadBone_wide": 52,
    "HeadBone_narrow": 53,
    "Head_wide": 54,
    "Head_narrow": 55,
    "head_shrink": 56,
    "head_stretch": 57,
    "head_fat": 58,
    "head_thin": 59,
    "cheek_wide": 60,
    "cheekbone_narrow": 61,
    "jawbone_Wide": 62,
    "jawbone_Narrow": 63,
    "jaw_m_wide": 64,
    "jaw_M_narrow": 65,
    "jaw_wide": 66,
    "jaw_narrow": 67,
    "jaw_up": 68,
    "jaw_lower": 69,
    "upperLip_Thick": 70,
    "upperLipSide_Thick": 71,
    "lowerLip_Thick": 72,
    "lowerLipSide_Thin": 73,
    "lowerLipSide_Thick": 74,
    "upperLip_Thin": 75,
    "lowerLip_Thin": 76,
    "mouth_magnify": 77,
    "mouth_shrink": 78,
    "lipCorner_Out": 79,
    "lipCorner_In": 80,
    "lipCorner_up": 81,
    "lipCorner_down": 82,
    "mouth_m_down": 83,
    "mouth_m_up": 84,
    "mouth_Up": 85,
    "mouth_Down": 86,
    "nostril_Out": 87,
    "nostril_In": 88,
    "noseTip_Up": 89,
    "noseTip_Down": 90,
    "nose_Up": 91,
    "nose_tall": 92,
    "nose_low": 93,
    "nose_Down": 94,
    "Eye_wide": 95,
    "Eye_shrink": 96,
    "Eye_up": 97,
    "Eye_down": 98,
    "Eye_in": 99,
    "Eye_out": 100,
    "Eye_close_L": 101,
    "Eye_close_R": 102,
    "Eye_open_L": 103,
    "Eye_open_R": 104,
    "Eye_upper_up_L": 105,
    "Eye_upper_up_R": 106,
    "Eye_upper_down_L": 107,
    "Eye_upper_down_R": 108,
    "Eye_upperBend_in_L": 109,
    "Eye_upperBend_in_R": 110,
    "Eye_upperBend_out_L": 111,
    "Eye_upperBend_out_R": 112,
    "Eye_downer_up_L": 113,
    "Eye_downer_up_R": 114,
    "Eye_downer_dn_L": 115,
    "Eye_downer_dn_R": 116,
    "Eye_downerBend_in_L": 117,
    "Eye_downerBend_in_R": 118,
    "Eye_downerBend_out_L": 119,
    "Eye_downerBend_out_R": 120,
    "Eye_outter_in": 121,
    "Eye_outter_out": 122,
    "Eye_outter_up": 123,
    "Eye_outter_down": 124,
    "Eye_inner_in": 125,
    "Eye_inner_out": 126,
    "Eye_inner_up": 127,
    "Eye_inner_down": 128,
    "jawTip_forward": 129,
    "jawTip_backward": 130,
    "jawBone_m_up": 131,
    "jawBone_m_down": 132,
    "upperLipSide_thin": 133,
    "mouth_side_up": 134,
    "mouth_side_down": 135,
    "mouth_forward": 136,
    "mouth_backward": 137,
    "noseTip_forward": 138,
    "noseTip_backward": 139,
    "noseTip_magnify": 140,
    "noseTip_shrink": 141,
    "nostril_up": 142,
    "nostril_down": 143,
    "noseBone_tall": 144,
    "noseBone_low": 145,
    "nose_wide": 146,
    "nose_shrink": 147,
    "Eye_forward": 148,
    "Eye_backward": 149
}
